{
    "keep": {
        "days": true,
        "amount": 14
    },
    "auditLog": "S:\\sande here there will be my code it does not take  big space\\key-management-system\\apps\\backend\\logs\\.0ab7cb63f6ffdbbd74c36fb32b180078c2b83d2e-audit.json",
    "files": [
        {
            "date": 1741763591801,
            "name": "S:\\sande here there will be my code it does not take  big space\\key-management-system\\apps\\backend\\logs\\2025-03-12-access.log",
            "hash": "92c44c2771b0b16e3aeddfd9e3601e32cd17ce642371fe3adc656d1443c03cca"
        },
        {
            "date": 1741846220257,
            "name": "S:\\sande here there will be my code it does not take  big space\\key-management-system\\apps\\backend\\logs\\2025-03-13-access.log",
            "hash": "a969b68176857325f7a452d2e4f2a0a4e93ca252f5cb573c82d379b08f0b95d0"
        },
        {
            "date": 1741941204499,
            "name": "S:\\sande here there will be my code it does not take  big space\\key-management-system\\apps\\backend\\logs\\2025-03-14-access.log",
            "hash": "70336432ff03e0d81e6ce58ae759093000811dd028e12740fe4f5220b2e8f2a3"
        }
    ],
    "hashType": "sha256"
}